{
  "publicPath": "/_nuxt/",
  "all": [
    "../server/index.spa.html",
    "../server/index.ssr.html",
    "0a25938.js",
    "1506720.js",
    "234d669.js",
    "37fa1bf.js",
    "57212da.js",
    "6055018.js",
    "794dd13.js",
    "8fad1a0.js",
    "LICENSES",
    "a53aefd.js",
    "aac5e4a.js",
    "ba9a0f8.js",
    "be40e30.js",
    "c3ac0d9.js",
    "d146fb3.js",
    "d9218ad.js",
    "dfd8a2f.js",
    "e07d147.js"
  ],
  "initial": [
    "c3ac0d9.js",
    "d9218ad.js",
    "0a25938.js",
    "37fa1bf.js"
  ],
  "async": [
    "1506720.js",
    "234d669.js",
    "57212da.js",
    "6055018.js",
    "794dd13.js",
    "8fad1a0.js",
    "a53aefd.js",
    "aac5e4a.js",
    "ba9a0f8.js",
    "be40e30.js",
    "d146fb3.js",
    "dfd8a2f.js",
    "e07d147.js"
  ],
  "modules": {
    "13852197": [
      2
    ],
    "17970986": [
      8
    ],
    "20838802": [
      2
    ],
    "21311546": [
      17
    ],
    "21395881": [
      17
    ],
    "21693774": [
      17
    ],
    "24873455": [
      18
    ],
    "26012107": [
      17
    ],
    "43689577": [
      2
    ],
    "46654768": [
      17
    ],
    "49423329": [
      4
    ],
    "50353764": [
      9
    ],
    "50683693": [
      17
    ],
    "53825531": [
      6,
      16,
      14
    ],
    "62618258": [
      2
    ],
    "62661965": [
      2
    ],
    "65608896": [
      14
    ],
    "75495424": [
      6,
      16,
      14
    ],
    "80920562": [
      17
    ],
    "85646048": [
      17
    ],
    "2675944e": [
      2
    ],
    "6b3f187e": [
      2
    ],
    "1bbaae35": [
      17
    ],
    "7197293a": [
      5
    ],
    "6c17ef26": [
      2
    ],
    "43b856f2": [
      2
    ],
    "d58d8ad2": [
      2
    ],
    "0158bc04": [
      2
    ],
    "5bc8c498": [
      2
    ],
    "4407f1bf": [
      2
    ],
    "0241eb7d": [
      2
    ],
    "3cee403a": [
      2
    ],
    "d411884e": [
      2
    ],
    "3d674440": [
      2
    ],
    "9d1eb542": [
      17
    ],
    "d0e29584": [
      17
    ],
    "a13a09e0": [
      17
    ],
    "3d15f755": [
      17
    ],
    "4a69dae2": [
      17
    ],
    "12884a6e": [
      17
    ],
    "09fe7f5c": [
      17
    ],
    "361bca92": [
      17
    ],
    "7fc629a6": [
      17
    ],
    "5cd665c8": [
      17
    ],
    "8f7d7a04": [
      17
    ],
    "3e2545c8": [
      2
    ],
    "599398c8": [
      17
    ],
    "32594b12": [
      17
    ],
    "40de941e": [
      17
    ],
    "0d8a474e": [
      17
    ],
    "7956c7eb": [
      17
    ],
    "6180be2f": [
      2
    ],
    "6f36467e": [
      17
    ],
    "4d0d1f63": [
      17
    ],
    "3ab82c3b": [
      17
    ],
    "62e76a9b": [
      17
    ],
    "268cdc11": [
      17
    ],
    "5389a926": [
      17
    ],
    "25b59f78": [
      17
    ],
    "22610c26": [
      2
    ],
    "4d10b7d7": [
      17
    ],
    "55d313d7": [
      17
    ],
    "0f186f76": [
      2
    ],
    "363d96c8": [
      2
    ],
    "48e42424": [
      2
    ],
    "43fb621e": [
      17
    ],
    "0c0fdbb6": [
      17
    ],
    "3fa198bc": [
      2
    ],
    "1d76f978": [
      2
    ],
    "8a42319e": [
      17
    ],
    "182f0011": [
      17
    ],
    "1710063d": [
      17
    ],
    "0b6ba72c": [
      17
    ],
    "ea558c20": [
      17
    ],
    "ae417672": [
      2
    ],
    "204e39fe": [
      17
    ],
    "2f42a758": [
      17
    ],
    "2e699f86": [
      17
    ],
    "f4840cb2": [
      17
    ],
    "4cbb1179": [
      5
    ],
    "f635ca0c": [
      5
    ],
    "11358a33": [
      5
    ],
    "348dfb03": [
      5
    ],
    "8bc9843c": [
      5
    ],
    "da256a2c": [
      5
    ],
    "5cd7b744": [
      5
    ],
    "12c9d850": [
      5
    ],
    "006df08e": [
      5
    ],
    "30b2ea78": [
      5
    ],
    "1757f72b": [
      5
    ],
    "27b38221": [
      5
    ],
    "1be59e06": [
      5
    ],
    "3e100f4a": [
      5
    ],
    "62078ffa": [
      5
    ],
    "1fb429f8": [
      5
    ],
    "dc68f64c": [
      5
    ],
    "d9d590f2": [
      5
    ],
    "0224dd28": [
      5
    ],
    "5c9f4a6e": [
      5
    ],
    "815b7912": [
      5
    ],
    "340da598": [
      5
    ],
    "3675d7e1": [
      5
    ],
    "6a3149c8": [
      5
    ],
    "3c4468dd": [
      5
    ],
    "86374ba6": [
      5
    ],
    "a184b788": [
      5
    ],
    "c410984c": [
      5
    ],
    "342ea97a": [
      5
    ],
    "2b4d0e20": [
      5
    ],
    "ada3d90e": [
      5
    ],
    "fddb3034": [
      5
    ],
    "daae5998": [
      5
    ],
    "1ab23494": [
      17
    ],
    "2fdfefbe": [
      17
    ],
    "c53c8fb2": [
      17
    ],
    "33861b32": [
      17
    ],
    "32acc550": [
      17
    ],
    "37cb2906": [
      17
    ],
    "0671cd8b": [
      17
    ],
    "4e087f40": [
      17
    ],
    "b369f64e": [
      17
    ],
    "397d16b2": [
      17
    ],
    "5c1f5a33": [
      2
    ],
    "d53af040": [
      2
    ],
    "365cead1": [
      17
    ],
    "4f8039e3": [
      2
    ],
    "703de058": [
      2
    ],
    "3457038d": [
      2
    ],
    "40e0c33a": [
      2
    ],
    "f4d87862": [
      2
    ],
    "4f7ff836": [
      2
    ],
    "5d9ec61a": [
      2
    ],
    "56da9ddc": [
      2
    ],
    "c6c3f078": [
      2
    ],
    "4c0c6212": [
      2
    ],
    "c33bf860": [
      2
    ],
    "a81d5052": [
      2
    ],
    "43e7aebb": [
      2
    ],
    "6d4a7e48": [
      2
    ],
    "0551eeb2": [
      17
    ],
    "98143b14": [
      17
    ],
    "b1e7515e": [
      17
    ],
    "39862e1e": [
      17
    ],
    "75fe20f6": [
      17
    ],
    "b47cd414": [
      17
    ],
    "5472d5f7": [
      2
    ],
    "68cc6477": [
      2
    ],
    "1da23dc2": [
      2
    ],
    "013bb740": [
      17
    ],
    "3edd8fd3": [
      2
    ],
    "2fb60ac9": [
      2
    ],
    "a9751c50": [
      2
    ],
    "5615cc5e": [
      17
    ],
    "bda258e6": [
      17
    ],
    "58665cd5": [
      17
    ],
    "5fca322c": [
      17
    ],
    "9ff70cf4": [
      17
    ],
    "0d94675e": [
      17
    ],
    "bedcf33c": [
      2
    ],
    "5cde26ca": [
      2
    ],
    "11af0416": [
      17
    ],
    "0f402c5c": [
      2
    ],
    "7d4b5a94": [
      2
    ],
    "6742e9d2": [
      2
    ],
    "54329bde": [
      5
    ],
    "6e0b7890": [
      2
    ],
    "d3ab1980": [
      2
    ],
    "0aa0c9ce": [
      17
    ],
    "74d5de9a": [
      2
    ],
    "23fa6d4e": [
      2
    ],
    "be54072a": [
      2
    ],
    "4b019b07": [
      5
    ],
    "1c11ea61": [
      17
    ],
    "39fe830e": [
      17
    ],
    "39788afc": [
      17
    ],
    "51d321e3": [
      17
    ],
    "0f51b35c": [
      17
    ],
    "80f9192c": [
      17
    ],
    "61e49ddd": [
      17
    ],
    "362f76d6": [
      2
    ],
    "47a9ff78": [
      2
    ],
    "653f7b8e": [
      17
    ],
    "f405ef94": [
      17
    ],
    "90850a18": [
      17
    ],
    "6ff0a578": [
      17
    ],
    "1faf8236": [
      5
    ],
    "6c3faab6": [
      2
    ],
    "a66eb80c": [
      2
    ],
    "e25f3326": [
      2
    ],
    "05a2b818": [
      2
    ],
    "27cb33c2": [
      2
    ],
    "21f46714": [
      2
    ],
    "6deca3fe": [
      2
    ],
    "01d16d58": [
      2
    ],
    "6924019e": [
      2
    ],
    "ab102318": [
      2
    ],
    "4834aa30": [
      5
    ],
    "a4a20d7c": [
      2
    ],
    "f69e31a0": [
      2
    ],
    "db7156fa": [
      2
    ],
    "41bba842": [
      2
    ],
    "08f5f9ac": [
      2
    ],
    "4c35addd": [
      2
    ],
    "7111c59e": [
      2
    ],
    "037817db": [
      2
    ],
    "7cd46396": [
      2
    ],
    "9b9c2460": [
      2
    ],
    "155f70d4": [
      2
    ],
    "3ea4063b": [
      2
    ],
    "1e44506e": [
      2
    ],
    "741314a7": [
      2
    ],
    "890da18e": [
      2
    ],
    "594ccf25": [
      2
    ],
    "6b8b1120": [
      2
    ],
    "7504c24c": [
      17
    ],
    "2b765108": [
      17
    ],
    "1aba6c6e": [
      17
    ],
    "4992a7f3": [
      17
    ],
    "0e0b5b3c": [
      17
    ],
    "69431f42": [
      17
    ],
    "63404dec": [
      17
    ],
    "451fce22": [
      17
    ],
    "6a6770da": [
      17
    ],
    "7bc1fe4a": [
      17
    ],
    "74a377cb": [
      17
    ],
    "d0730b50": [
      17
    ],
    "4a1ba8c0": [
      17
    ],
    "501f1a4f": [
      17
    ],
    "2a57caac": [
      2
    ],
    "326a49c0": [
      2
    ],
    "eefec51c": [
      17
    ],
    "c99ab634": [
      17
    ],
    "57e5c7eb": [
      17
    ],
    "9c22ab84": [
      17
    ],
    "88bb4aae": [
      2
    ],
    "ae42689c": [
      2
    ],
    "63c075ee": [
      2
    ],
    "422c3bd3": [
      2
    ],
    "6e5b4e8e": [
      2
    ],
    "84460c54": [
      2
    ],
    "7ac6efb6": [
      2
    ],
    "8ef2c2ea": [
      17
    ],
    "3c25c9ef": [
      17
    ],
    "663e87e1": [
      2
    ],
    "1537e9ff": [
      2
    ],
    "cbf66fd4": [
      2
    ],
    "230694e6": [
      2
    ],
    "3c1afb75": [
      2
    ],
    "e0daf4ae": [
      2
    ],
    "04b24f1a": [
      2
    ],
    "745c66f7": [
      2
    ],
    "5a2675bc": [
      17
    ],
    "be7634f0": [
      17
    ],
    "e29bf9aa": [
      17
    ],
    "2931b6dd": [
      17
    ],
    "7e88fff0": [
      17
    ],
    "de2426d6": [
      17
    ],
    "2f2a74da": [
      17
    ],
    "4971ef7b": [
      17
    ],
    "f3adc624": [
      17
    ],
    "30b28e1b": [
      17
    ],
    "13c1a861": [
      17
    ],
    "1dbd8f54": [
      17
    ],
    "5d192abf": [
      17
    ],
    "1970bf0c": [
      17
    ],
    "636a6e8b": [
      2
    ],
    "2cc3a2d3": [
      2
    ],
    "7bfc7120": [
      2
    ],
    "eb1cd5ea": [
      2
    ],
    "0e9ebe06": [
      2
    ],
    "30e963e5": [
      2
    ],
    "0f436cc2": [
      2
    ],
    "44d84cfc": [
      2
    ],
    "0a299b08": [
      2
    ],
    "6106f816": [
      2
    ],
    "298d7918": [
      2
    ],
    "ecf116be": [
      17
    ],
    "3a7719fc": [
      5
    ],
    "01f16598": [
      5
    ],
    "6d33dd21": [
      5
    ],
    "fc4c87f4": [
      17
    ],
    "3a6849b0": [
      2
    ],
    "ac321390": [
      2
    ],
    "2f34a231": [
      17
    ],
    "11a42b93": [
      17
    ],
    "4842fbbc": [
      17
    ],
    "f9315c2c": [
      5
    ],
    "f93c314e": [
      5
    ],
    "8c4f7d32": [
      5
    ],
    "c325fb26": [
      5
    ],
    "57b6d6d3": [
      5
    ],
    "1d63eb44": [
      2
    ],
    "f287b388": [
      2
    ],
    "396b62f0": [
      2
    ],
    "223fb1fe": [
      2
    ],
    "3ad0501a": [
      2
    ],
    "7af19b53": [
      2
    ],
    "3967fece": [
      2
    ],
    "cb32f284": [
      2
    ],
    "7d4b019e": [
      2
    ],
    "e4c3c1c4": [
      5
    ],
    "3df6302a": [
      2
    ],
    "be6289ec": [
      2
    ],
    "15f427bc": [
      2
    ],
    "3020fb1c": [
      2
    ],
    "a4380ae0": [
      2
    ],
    "62ccfae2": [
      5
    ],
    "5f4833fa": [
      5
    ],
    "9bebf01c": [
      5
    ],
    "4105d454": [
      5
    ],
    "41db065f": [
      5
    ],
    "40f3a57c": [
      5
    ],
    "41e5ef47": [
      5
    ],
    "41c0347a": [
      5
    ],
    "476d006e": [
      2
    ],
    "0f100f71": [
      2
    ],
    "6c49182f": [
      2
    ],
    "4f8c2e58": [
      2
    ],
    "6d2b68f7": [
      2
    ],
    "02e43904": [
      2
    ],
    "a985f868": [
      2
    ],
    "dd96a832": [
      2
    ],
    "deb16fa0": [
      2
    ],
    "f7c40892": [
      5
    ],
    "095b5738": [
      5
    ],
    "f70cce36": [
      17
    ],
    "176173ca": [
      17
    ],
    "32993d9b": [
      17
    ],
    "4455371a": [
      17
    ],
    "ecb3855a": [
      17
    ],
    "36d4462c": [
      17
    ],
    "7b712afd": [
      17
    ],
    "4655941c": [
      17
    ],
    "2d7a1a4c": [
      17
    ],
    "41d933a0": [
      17
    ],
    "30705c0c": [
      17
    ],
    "5020e304": [
      17
    ],
    "16e944b2": [
      17
    ],
    "95d2af5c": [
      17
    ],
    "970b18b6": [
      5
    ],
    "f3d48538": [
      5
    ],
    "6d6fa157": [
      2
    ],
    "7bcb4fd6": [
      2
    ],
    "acdb4bda": [
      2
    ],
    "4a3aafdc": [
      2
    ],
    "ec306092": [
      2
    ],
    "03ba3a3e": [
      2
    ],
    "038aa440": [
      2
    ],
    "1d1364f2": [
      2
    ],
    "c8525334": [
      2
    ],
    "2bce067b": [
      2
    ],
    "788851c8": [
      2
    ],
    "4de470e8": [
      2
    ],
    "0ed9434b": [
      2
    ],
    "3bda9980": [
      2
    ],
    "75d81320": [
      2
    ],
    "796bace8": [
      2
    ],
    "3dd648ce": [
      2
    ],
    "317a2696": [
      2
    ],
    "9a6bfbfe": [
      2
    ],
    "a97b5fd2": [
      5
    ],
    "fcf65b30": [
      2
    ],
    "39ef43f9": [
      5
    ],
    "4d8ff2a4": [
      2
    ],
    "277113da": [
      2
    ],
    "6efe0608": [
      2
    ],
    "ca486648": [
      2
    ],
    "18f70faa": [
      2
    ],
    "00c62dfa": [
      2
    ],
    "52b2b222": [
      2
    ],
    "04c60a05": [
      2
    ],
    "27f9197f": [
      2
    ],
    "13d498eb": [
      2
    ],
    "71380d1e": [
      2
    ],
    "8855dfc0": [
      2
    ],
    "15c94876": [
      2
    ],
    "90a7a678": [
      2
    ],
    "7a3f834e": [
      2
    ],
    "329ae722": [
      2
    ],
    "70128b7c": [
      2
    ],
    "7c2b98d8": [
      17
    ],
    "5be61e66": [
      17
    ],
    "31fd9762": [
      17
    ],
    "0b5b9a09": [
      17
    ],
    "0fe35afe": [
      17
    ],
    "17619c18": [
      17
    ],
    "5c4197c0": [
      17
    ],
    "7bf21eb8": [
      17
    ],
    "55167ef4": [
      17
    ],
    "6e734508": [
      17
    ],
    "34c88a52": [
      5
    ],
    "7327330c": [
      5
    ],
    "3f3a5ef8": [
      5
    ],
    "01ba32be": [
      5
    ],
    "4dacba61": [
      17
    ],
    "13fef2d8": [
      17
    ],
    "592c4471": [
      5
    ],
    "c61771aa": [
      5
    ],
    "6d29b2bd": [
      17
    ],
    "1aa64fc3": [
      17
    ],
    "a1df5dc8": [
      17
    ],
    "1723739c": [
      17
    ],
    "efe13316": [
      17
    ],
    "48e8fc35": [
      17
    ],
    "1957629d": [
      2
    ],
    "c0ab8d14": [
      2
    ],
    "74385f3a": [
      2
    ],
    "5966e7c0": [
      2
    ],
    "f4695b9c": [
      2
    ],
    "33c09e13": [
      2
    ],
    "4044c46a": [
      17
    ],
    "e91b4da6": [
      2
    ],
    "ec28b99a": [
      2
    ],
    "f6bfa392": [
      2
    ],
    "19a4e989": [
      2
    ],
    "7fbc6fd9": [
      2
    ],
    "6a9d744f": [
      2
    ],
    "03fe8763": [
      2
    ],
    "5dc05181": [
      2
    ],
    "6fc32cca": [
      2
    ],
    "349bb36a": [
      2
    ],
    "1c8f650b": [
      2
    ],
    "c23259de": [
      2
    ],
    "00185912": [
      17
    ],
    "4953d994": [
      17
    ],
    "b6e8104a": [
      17
    ],
    "27c17292": [
      17
    ],
    "21c654e5": [
      17
    ],
    "6fade2b0": [
      17
    ],
    "2ddfb62c": [
      17
    ],
    "568f579a": [
      2
    ],
    "203d1e13": [
      2
    ],
    "228d0731": [
      2
    ],
    "184e6ea0": [
      2
    ],
    "aad72890": [
      2
    ],
    "6ec2f5d1": [
      2
    ],
    "617c2c83": [
      2
    ],
    "c8e20c94": [
      14
    ],
    "0e97e714": [
      14
    ],
    "5d4cf303": [
      14
    ],
    "758e4080": [
      14
    ],
    "4701b717": [
      14
    ],
    "c6bd2f40": [
      14
    ],
    "f62fd94c": [
      12,
      14
    ],
    "631858e2": [
      4
    ],
    "3389b310": [
      14
    ],
    "e5204c74": [
      16
    ],
    "416af005": [
      16
    ],
    "dcd6e5e2": [
      16
    ],
    "75a439f8": [
      16
    ],
    "fc303852": [
      16
    ],
    "7d7002aa": [
      12,
      14
    ],
    "b3108338": [
      12,
      14
    ],
    "2f4f0a3f": [
      4
    ],
    "15c98945": [
      4
    ],
    "4ef4de5e": [
      3
    ],
    "7cc96b1f": [
      7
    ],
    "c7db0138": [
      6,
      16,
      14
    ],
    "5a4e9621": [
      6,
      16,
      14
    ],
    "801a45a6": [
      6,
      16,
      14
    ],
    "54e00535": [
      6,
      16,
      14
    ],
    "ed78c2ce": [
      6,
      16,
      14
    ],
    "e39341fa": [
      6,
      16,
      14
    ],
    "50fd382e": [
      6,
      16,
      14
    ],
    "ba82149c": [
      6,
      16,
      14
    ],
    "13ff41bd": [
      6,
      16,
      14
    ],
    "c2892200": [
      6,
      16,
      14
    ],
    "3a4fc45b": [
      6,
      16,
      14
    ],
    "cb48a724": [
      6,
      16,
      14
    ],
    "a769a0ba": [
      6,
      16,
      14
    ],
    "1e98d5cc": [
      6,
      16,
      14
    ],
    "032a88f2": [
      6,
      16,
      14
    ],
    "43fad85e": [
      6,
      16,
      14
    ],
    "0fd86f6c": [
      6,
      16,
      14
    ],
    "170a376f": [
      6,
      16,
      14
    ],
    "52d9abda": [
      6,
      16,
      14
    ],
    "687f1d90": [
      6,
      16,
      14
    ],
    "4a29c50f": [
      6,
      16,
      14
    ],
    "671a8586": [
      6,
      16,
      14
    ],
    "9e246eca": [
      6,
      16,
      14
    ],
    "bcdd9108": [
      6,
      16,
      14
    ],
    "dc1825b0": [
      6,
      16,
      14
    ],
    "2d3005d8": [
      18
    ],
    "193acaea": [
      18
    ],
    "5d04be39": [
      18
    ],
    "95a67604": [
      18
    ],
    "152ad4a5": [
      18
    ],
    "1559801e": [
      18
    ],
    "66f61f1a": [
      18
    ],
    "2ed9f39d": [
      18
    ],
    "57416a42": [
      18
    ],
    "ffb79f78": [
      18
    ],
    "18b1da91": [
      18
    ],
    "e76ca834": [
      18
    ],
    "18c7315c": [
      18
    ],
    "107a9008": [
      18
    ],
    "66a244ae": [
      18
    ],
    "1d1ad950": [
      18
    ],
    "e1ce6a06": [
      18
    ],
    "3eccb8fa": [
      18
    ],
    "58f22bbe": [
      18
    ],
    "f37d1de0": [
      18
    ],
    "2a74bc1b": [
      18
    ],
    "0fe6bd12": [
      12,
      14
    ],
    "1c53e7ff": [
      12,
      14
    ],
    "79c0be62": [
      12,
      14
    ],
    "73f05b6b": [
      12,
      14
    ],
    "4aefab14": [
      12,
      14
    ],
    "27a5b2d2": [
      12,
      14
    ],
    "37329a85": [
      12,
      14
    ],
    "36dbbc93": [
      12,
      14
    ],
    "490b4b7e": [
      12,
      14
    ],
    "54ba5542": [
      12,
      14
    ],
    "57908cb2": [
      12,
      14
    ],
    "e33965a8": [
      12,
      14
    ],
    "4270b3ad": [
      12,
      14
    ],
    "3e6f1956": [
      12,
      14
    ],
    "a3f0ac74": [
      12,
      14
    ],
    "2c41e298": [
      12,
      14
    ],
    "5a7e659c": [
      19,
      14
    ],
    "e8cfe78a": [
      19,
      14
    ],
    "a10ddfc2": [
      19,
      14
    ],
    "278a064f": [
      19,
      14
    ],
    "679f268b": [
      19,
      14
    ],
    "52b1994e": [
      19,
      14
    ],
    "3120c076": [
      19,
      14
    ],
    "22f9da88": [
      19,
      14
    ],
    "6614256b": [
      19,
      14
    ],
    "b39ca638": [
      19,
      14
    ],
    "634cf5ec": [
      19,
      14
    ],
    "325ab4f4": [
      19,
      14
    ],
    "513aef02": [
      19,
      14
    ],
    "534a73f8": [
      19,
      14
    ],
    "ab71bd50": [
      19,
      14
    ],
    "64dbf2e8": [
      4
    ],
    "5c101e15": [
      4
    ],
    "818b1826": [
      4
    ],
    "4c6b5081": [
      4
    ],
    "71bd8101": [
      4
    ],
    "345da138": [
      4
    ],
    "18249f28": [
      4
    ],
    "6e8cfc27": [
      4
    ],
    "8a790bd6": [
      4
    ],
    "6e500eea": [
      4
    ],
    "69b188d1": [
      4
    ],
    "583a7eda": [
      4
    ],
    "4f8e5a12": [
      4
    ],
    "4a002836": [
      4
    ],
    "769ca92e": [
      9
    ],
    "553bbba6": [
      9
    ],
    "60a3a57d": [
      9
    ],
    "e4ef8ece": [
      9
    ],
    "117e803e": [
      9
    ],
    "1cb0fc77": [
      9
    ],
    "02867a38": [
      9
    ],
    "2c11d6e3": [
      9
    ],
    "73d4dd4c": [
      9
    ],
    "7c5aa49f": [
      11,
      14
    ],
    "0038100f": [
      11,
      14
    ],
    "16c48052": [
      11,
      14
    ],
    "0a6d01ba": [
      11,
      14
    ],
    "3fd57c84": [
      11,
      14
    ],
    "43feabf8": [
      11,
      14
    ],
    "78061da5": [
      13
    ],
    "06170390": [
      13
    ],
    "2302510c": [
      13
    ],
    "07196368": [
      13
    ],
    "d7c15d10": [
      13
    ],
    "360a29a6": [
      8
    ],
    "9f89771c": [
      8
    ],
    "791ec9aa": [
      8
    ],
    "0a6ac697": [
      8
    ]
  },
  "assetsMapping": {
    "7ea24c87": [
      "0a25938.js"
    ],
    "bba68bf6": [
      "1506720.js",
      "6055018.js",
      "794dd13.js"
    ],
    "6a7d3fe2": [
      "234d669.js"
    ],
    "1a3ae26b": [
      "37fa1bf.js"
    ],
    "2a130dde": [
      "57212da.js"
    ],
    "f096985e": [
      "8fad1a0.js"
    ],
    "2aff1868": [
      "a53aefd.js"
    ],
    "6d7698ba": [
      "aac5e4a.js"
    ],
    "06d6d812": [
      "ba9a0f8.js"
    ],
    "324f2299": [
      "be40e30.js"
    ],
    "6fca0322": [
      "c3ac0d9.js"
    ],
    "f45ff1a6": [
      "d146fb3.js"
    ],
    "085a35c4": [
      "d9218ad.js"
    ],
    "febe4776": [
      "dfd8a2f.js"
    ],
    "67c13ec2": [
      "e07d147.js"
    ]
  }
}